liblathe-0.0.5.dist-info/METADATA
liblathe-0.0.5.dist-info/RECORD
liblathe-0.0.5.dist-info/top_level.txt
liblathe-0.0.5.dist-info/WHEEL
liblathe-0.0.5.dist-info/LICENSE
liblathe/__init__.py
liblathe/version.py
liblathe/tool/tool.py
liblathe/op/rough.py
liblathe/op/face.py
liblathe/op/profile.py
liblathe/op/base.py
liblathe/op/partoff.py
liblathe/gcode/command.py
liblathe/gcode/path.py
liblathe/base/segmentgroup.cpython-311-i386-linux-gnu.so
liblathe/base/point.cpython-311-i386-linux-gnu.so
liblathe/base/boundbox.cpython-311-i386-linux-gnu.so
liblathe/base/segment.cpython-311-i386-linux-gnu.so
