Metadata-Version: 2.1
Name: liblathe
Version: 0.0.5
Summary: Python library for generating lathe paths and gcode 
Home-page: https://github.com/dubstar-04/LibLathe
Author: Daniel Wood
Author-email: s.d.wood.82@googlemail.com
License: GPL2
Keywords: lathe turning CAD CAM CNC
Classifier: Development Status :: 2 - Pre-Alpha
Classifier: Intended Audience :: Science/Research
Classifier: License :: OSI Approved :: BSD License
Classifier: Operating System :: POSIX :: Linux
Classifier: Programming Language :: Python :: 3
Classifier: Programming Language :: Python :: 3.10
Classifier: Programming Language :: Python :: 3.11
Classifier: Programming Language :: Python :: 3.12
Classifier: Programming Language :: Python :: 3.13
License-File: LICENSE
Requires-Dist: pillow
